unspooler/__init__.py
unspooler/unspooler.py
unspooler-1.0.0.dist-info/DESCRIPTION.rst
unspooler-1.0.0.dist-info/METADATA
unspooler-1.0.0.dist-info/RECORD
unspooler-1.0.0.dist-info/WHEEL
unspooler-1.0.0.dist-info/metadata.json
unspooler-1.0.0.dist-info/top_level.txt
