Metadata-Version: 2.0
Name: unspooler
Version: 1.0.0
Summary: unspooler
Home-page: https://github.com/dfreelon/unspooler/
Author: Deen Freelon
Author-email: dfreelon@gmail.com
License: UNKNOWN
Download-URL: https://github.com/dfreelon/unspooler/tarball/1.0
Keywords: hyperlink,shortlink,bit.ly,unshorten
Platform: UNKNOWN
Requires-Dist: requests
